comapsmarthome_public_api/__init__.py
comapsmarthome_public_api/archiving_service.py
comapsmarthome_public_api/client_auth.py
comapsmarthome_public_api/comap_smart_home.py
comapsmarthome_public_api/measurement_service.py
comapsmarthome_public_api/park_service_client.py
comapsmarthome_public_api/thermal_service.py
comapsmarthome_public_api/user_service.py
comapsmarthome_public_api-0.0.9.dist-info/LICENSE
comapsmarthome_public_api-0.0.9.dist-info/METADATA
comapsmarthome_public_api-0.0.9.dist-info/WHEEL
comapsmarthome_public_api-0.0.9.dist-info/top_level.txt
comapsmarthome_public_api-0.0.9.dist-info/RECORD
