Metadata-Version: 2.1
Name: comapsmarthome-public-api
Version: 0.0.9
Summary: Comap Smart Home public API python module
Home-page: https://gitlab.com/melec/comapsmarthome_public_api_python
Author: Melec Petit-Pierre
Author-email: melec.petit-pierre@comap.eu
License: MIT
Platform: UNKNOWN
Classifier: Programming Language :: Python :: 3
Classifier: License :: OSI Approved :: MIT License
Classifier: Operating System :: OS Independent
Requires-Python: >=3.6
License-File: LICENSE
Requires-Dist: requests
Requires-Dist: boto3
Requires-Dist: python-dateutil
Requires-Dist: pytz
